petropy/__init__.py
petropy/datasets.py
petropy/download.py
petropy/electrofacies.py
petropy/graphs.py
petropy/log.py
petropy/data/42303347740000.las
petropy/data/curve_alias.xml
petropy/data/default_gas_full_template.xml
petropy/data/default_multimin_gas_sum_template.xml
petropy/data/default_multimin_gas_template.xml
petropy/data/default_multimin_oil_sum_template.xml
petropy/data/default_multimin_oil_template.xml
petropy/data/default_oil_full_template.xml
petropy/data/default_raw_template.xml
petropy/data/fluid_properties_parameters.csv
petropy/data/multimineral_parameters.csv
petropy/data/tops.csv
petropy-0.1.6.dist-info/DESCRIPTION.rst
petropy-0.1.6.dist-info/METADATA
petropy-0.1.6.dist-info/RECORD
petropy-0.1.6.dist-info/WHEEL
petropy-0.1.6.dist-info/metadata.json
petropy-0.1.6.dist-info/top_level.txt
