Metadata-Version: 2.0
Name: petropy
Version: 0.1.6
Summary: A package to calculate petrophysical properties for formation evaluation.
Home-page: https://github.com/toddheitmann/petropy
Author: Todd Heitmann
Author-email: toddheitmann@protonmail.com
License: UNKNOWN
Keywords: petrophysics,formation evaluation,reservoir characterization,Oil and Gas
Platform: UNKNOWN
Classifier: Intended Audience :: Customer Service
Classifier: Intended Audience :: Developers
Classifier: Intended Audience :: Education
Classifier: Intended Audience :: End Users/Desktop
Classifier: Intended Audience :: Other Audience
Classifier: Intended Audience :: Science/Research
Classifier: License :: OSI Approved :: MIT License
Classifier: Natural Language :: English
Classifier: Operating System :: OS Independent
Classifier: Programming Language :: Python :: 2
Classifier: Programming Language :: Python :: 3
Classifier: Topic :: Scientific/Engineering
Classifier: Topic :: System :: Filesystems
Classifier: Topic :: Scientific/Engineering :: Information Analysis
Requires-Dist: cchardet
Requires-Dist: lasio
Requires-Dist: matplotlib
Requires-Dist: numpy
Requires-Dist: pandas
Requires-Dist: scikit-learn
Requires-Dist: scipy
